{"program": [
    {"statement": [{"usingStmt": [
        {"text": "using"},
        {"reference": [
            {"identifier": [{"text": "dbo"}]},
            {"text": "."},
            {"identifier": [{"text": "sport"}]}
        ]}
    ]}]},
    {"statement": [{"usingStmt": [
        {"text": "using"},
        {"reference": [
            {"identifier": [{"text": "dbo"}]},
            {"text": "."},
            {"identifier": [{"text": "food"}]}
        ]}
    ]}]},
    {"statement": [{"usingStmt": [
        {"text": "using"},
        {"identifier": [{"text": "person"}]},
        {"text": "."},
        {"identifier": [{"text": "ID"}]},
        {"text": "="},
        {"literal": [{"text": "1"}]}
    ]}]},
    {"statement": [{"generateStmt": [
        {"text": "generate"},
        {"identifier": [{"text": "training"}]},
        {"text": "("},
        {"paramList": [
            {"param": [
                {"identifier": [{"text": "time"}]},
                {"text": "("},
                {"value": [{"reference": [{"identifier": [{"text": "avg"}]}]}]},
                {"text": ")"}
            ]},
            {"text": ","},
            {"param": [
                {"identifier": [{"text": "amount"}]},
                {"text": "("},
                {"value": [{"reference": [{"identifier": [{"text": "avg_not_specified"}]}]}]},
                {"text": ")"}
            ]},
            {"text": ","},
            {"param": [
                {"identifier": [{"text": "type"}]},
                {"text": "("},
                {"value": [{"reference": [{"identifier": [{"text": "w_gear_not_specified"}]}]}]},
                {"text": ")"}
            ]},
            {"text": ","},
            {"param": [
                {"identifier": [{"text": "goal"}]},
                {"text": "("},
                {"value": [{"reference": [{"identifier": [{"text": "fit"}]}]}]},
                {"text": ")"}
            ]},
            {"text": ","},
            {"param": [
                {"identifier": [{"text": "Person"}]},
                {"text": "("},
                {"value": [{"reference": [{"identifier": [{"text": "person"}]}]}]},
                {"text": ")"}
            ]}
        ]},
        {"text": ")"}
    ]}]},
    {"statement": [{"outputStmt": [
        {"text": "output"},
        {"expression": [{"reference": [{"identifier": [{"text": "training"}]}]}]},
        {"text": "as"},
        {"identifier": [{"text": "description"}]},
        {"text": "table"}
    ]}]},
    {"statement": [{"loopStmt": [{"whileStmt": [
        {"text": "while"},
        {"text": "("},
        {"condition": [
            {"reference": [
                {"identifier": [{"text": "time"}]},
                {"text": "."},
                {"identifier": [{"text": "max"}]}
            ]},
            {"text": "!="},
            {"text": "done"}
        ]},
        {"text": ")"},
        {"block": [
            {"text": "{"},
            {"statement": [{"outputStmt": [
                {"text": "output"},
                {"expression": [{"reference": [
                    {"identifier": [{"text": "rep"}]},
                    {"text": "."},
                    {"identifier": [{"text": "time"}]}
                ]}]}
            ]}]},
            {"statement": [{"outputStmt": [
                {"text": "output"},
                {"expression": [{"reference": [
                    {"identifier": [{"text": "rest"}]},
                    {"text": "."},
                    {"identifier": [{"text": "time"}]}
                ]}]}
            ]}]},
            {"text": "}"}
        ]}
    ]}]}]}
]}